customgpt_cli/__init__.py
customgpt_cli/cli.py
customgpt_cli/openapi.json
customgpt_cli-0.1.3.dist-info/METADATA
customgpt_cli-0.1.3.dist-info/WHEEL
customgpt_cli-0.1.3.dist-info/entry_points.txt
customgpt_cli-0.1.3.dist-info/RECORD
