Metadata-Version: 2.1
Name: customgpt-cli
Version: 0.1.3
Summary: No-code AI agent creation platform for enterprise knowledge automation
Home-page: https://customgpt.ai
Keywords: ai,agent,cli,automation,enterprise
Author: CustomGPT Team
Author-email: support@customgpt.ai
Requires-Python: >=3.8,<4.0
Classifier: Programming Language :: Python :: 3
Classifier: Programming Language :: Python :: 3.8
Classifier: Programming Language :: Python :: 3.9
Classifier: Programming Language :: Python :: 3.10
Classifier: Programming Language :: Python :: 3.11
Classifier: Programming Language :: Python :: 3.12
Classifier: Programming Language :: Python :: 3.13
Requires-Dist: customgpt-client (>=1.1.6)
Requires-Dist: tabulate (>=0.9.0)
Project-URL: Repository, https://github.com/customgpt/customgpt-cli
